RPLCD/__init__.py
RPLCD/common.py
RPLCD/compat.py
RPLCD/contextmanagers.py
RPLCD/gpio.py
RPLCD/i2c.py
RPLCD/lcd.py
RPLCD/pigpio.py
RPLCD/codecs/__init__.py
RPLCD/codecs/hd44780_a00.py
RPLCD/codecs/hd44780_a02.py
RPLCD/codecs/st7066_0b.py
RPLCD_Tests/__init__.py
RPLCD_Tests/entrypoint.py
RPLCD_Tests/show_charmap.py
RPLCD_Tests/testsuite_16x2.py
RPLCD_Tests/testsuite_20x4.py
lcdtests/__init__.py
lcdtests/show_charmap.py
lcdtests/testsuite_16x2.py
lcdtests/testsuite_20x4.py
RPLCD-1.3.0.dist-info/LICENSE
RPLCD-1.3.0.dist-info/METADATA
RPLCD-1.3.0.dist-info/WHEEL
RPLCD-1.3.0.dist-info/entry_points.txt
RPLCD-1.3.0.dist-info/top_level.txt
RPLCD-1.3.0.dist-info/RECORD
