Metadata-Version: 1.1
Name: RPLCD
Version: 1.3.0
Summary: A Raspberry Pi LCD library for the widely used Hitachi HD44780 controller.
Home-page: https://github.com/dbrgn/RPLCD
Author: Danilo Bargen
Author-email: mail@dbrgn.ch
License: MIT
Keywords: raspberry,raspberry pi,lcd,liquid crystal,hitachi,hd44780
Platform: any
Classifier: Development Status :: 5 - Production/Stable
Classifier: Environment :: Other Environment
Classifier: Intended Audience :: Developers
Classifier: License :: OSI Approved :: MIT License
Classifier: Operating System :: POSIX
Classifier: Programming Language :: Python :: 2
Classifier: Programming Language :: Python :: 2.7
Classifier: Programming Language :: Python :: 3
Classifier: Programming Language :: Python :: 3.3
Classifier: Programming Language :: Python :: 3.4
Classifier: Programming Language :: Python :: 3.5
Classifier: Programming Language :: Python :: 3.6
Classifier: Topic :: System :: Hardware :: Hardware Drivers
Classifier: Topic :: Software Development :: Libraries :: Python Modules
